X3TianRumenMysqlQianfengJiaoyu/README.md
X3TianRumenMysqlQianfengJiaoyu/__init__.py
X3TianRumenMysqlQianfengJiaoyu/__main__.py
X3TianRumenMysqlQianfengJiaoyu/file.epub
X3TianRumenMysqlQianfengJiaoyu/index.html
X3TianRumenMysqlQianfengJiaoyu/css/__init__.py
X3TianRumenMysqlQianfengJiaoyu/css/annotations.css
X3TianRumenMysqlQianfengJiaoyu/css/main.css
X3TianRumenMysqlQianfengJiaoyu/css/normalize.css
X3TianRumenMysqlQianfengJiaoyu/css/popup.css
X3TianRumenMysqlQianfengJiaoyu/font/__init__.py
X3TianRumenMysqlQianfengJiaoyu/font/fontello.eot
X3TianRumenMysqlQianfengJiaoyu/font/fontello.svg
X3TianRumenMysqlQianfengJiaoyu/font/fontello.ttf
X3TianRumenMysqlQianfengJiaoyu/font/fontello.woff
X3TianRumenMysqlQianfengJiaoyu/img/__init__.py
X3TianRumenMysqlQianfengJiaoyu/img/annotator-glyph-sprite.png
X3TianRumenMysqlQianfengJiaoyu/img/annotator-icon-sprite.png
X3TianRumenMysqlQianfengJiaoyu/img/apple-touch-icon.png
X3TianRumenMysqlQianfengJiaoyu/img/cancelfullscreen.png
X3TianRumenMysqlQianfengJiaoyu/img/close.png
X3TianRumenMysqlQianfengJiaoyu/img/fullscreen.png
X3TianRumenMysqlQianfengJiaoyu/img/loader.gif
X3TianRumenMysqlQianfengJiaoyu/img/menu-icon.png
X3TianRumenMysqlQianfengJiaoyu/img/save.png
X3TianRumenMysqlQianfengJiaoyu/img/saved.png
X3TianRumenMysqlQianfengJiaoyu/img/settings-s.png
X3TianRumenMysqlQianfengJiaoyu/img/settings.png
X3TianRumenMysqlQianfengJiaoyu/img/star.png
X3TianRumenMysqlQianfengJiaoyu/js/__init__.py
X3TianRumenMysqlQianfengJiaoyu/js/epub.js
X3TianRumenMysqlQianfengJiaoyu/js/epub.min.js
X3TianRumenMysqlQianfengJiaoyu/js/epub.min.map
X3TianRumenMysqlQianfengJiaoyu/js/hooks.min.js
X3TianRumenMysqlQianfengJiaoyu/js/hooks.min.map
X3TianRumenMysqlQianfengJiaoyu/js/reader.js
X3TianRumenMysqlQianfengJiaoyu/js/reader.js.map
X3TianRumenMysqlQianfengJiaoyu/js/reader.min.js
X3TianRumenMysqlQianfengJiaoyu/js/reader.min.map
X3TianRumenMysqlQianfengJiaoyu/js/hooks/__init__.py
X3TianRumenMysqlQianfengJiaoyu/js/hooks/extensions/__init__.py
x3_tian_rumen_mysql_qianfeng_jiaoyu-2024.3.2.0.dist-info/METADATA
x3_tian_rumen_mysql_qianfeng_jiaoyu-2024.3.2.0.dist-info/WHEEL
x3_tian_rumen_mysql_qianfeng_jiaoyu-2024.3.2.0.dist-info/entry_points.txt
x3_tian_rumen_mysql_qianfeng_jiaoyu-2024.3.2.0.dist-info/top_level.txt
x3_tian_rumen_mysql_qianfeng_jiaoyu-2024.3.2.0.dist-info/RECORD
